MANIFEST.in
README.rst
requirements.txt
setup.cfg
setup.py
doc/Makefile
doc/codegen.rst
doc/conf.py
doc/eval.rst
doc/expansion.rst
doc/index.rst
doc/interactions.rst
doc/kernel.rst
doc/misc.rst
examples/curve-pot.py
examples/curve.py
examples/expansion-toys.py
examples/fourier.py
examples/sym-exp-complexity.py
sumpy/__init__.py
sumpy/_git_rev.py
sumpy/array_context.py
sumpy/assignment_collection.py
sumpy/codegen.py
sumpy/cse.py
sumpy/distributed.py
sumpy/e2e.py
sumpy/e2p.py
sumpy/fmm.py
sumpy/kernel.py
sumpy/p2e.py
sumpy/p2p.py
sumpy/point_calculus.py
sumpy/qbx.py
sumpy/symbolic.py
sumpy/tools.py
sumpy/toys.py
sumpy/version.py
sumpy/visualization.py
sumpy.egg-info/PKG-INFO
sumpy.egg-info/SOURCES.txt
sumpy.egg-info/dependency_links.txt
sumpy.egg-info/requires.txt
sumpy.egg-info/top_level.txt
sumpy/expansion/__init__.py
sumpy/expansion/diff_op.py
sumpy/expansion/level_to_order.py
sumpy/expansion/local.py
sumpy/expansion/m2l.py
sumpy/expansion/multipole.py
test/test_codegen.py
test/test_cse.py
test/test_distributed.py
test/test_fmm.py
test/test_kernels.py
test/test_matrixgen.py
test/test_misc.py
test/test_qbx.py
test/test_tools.py